myredditbot2/__init__.py
myredditbot2/topusers.py
myredditbot2-0.2.dist-info/METADATA
myredditbot2-0.2.dist-info/WHEEL
myredditbot2-0.2.dist-info/entry_points.txt
myredditbot2-0.2.dist-info/top_level.txt
myredditbot2-0.2.dist-info/RECORD
