Metadata-Version: 2.1
Name: myredditbot2
Version: 0.2
Requires-Dist: requests
Requires-Dist: beautifulsoup4
